cosvar/__init__.py
cosvar/dlin.py
cosvar/intpk4.py
cosvar/pofk.py
cosvar/pyCV.py
cosvar/quickcv.py
cosvar/rz.py
pyCV/__init__.py
pyCV/dlin.py
pyCV/intpk4.py
pyCV/pofk.py
pyCV/pyCV.py
pyCV/quickcv.py
pyCV/rz.py
src/__init__.py
src/dlin.py
src/intpk4.py
src/pofk.py
src/pyCV.py
src/quickcv.py
src/rz.py
src/cosvar/__init__.py
src/cosvar/dlin.py
src/cosvar/intpk4.py
src/cosvar/pofk.py
src/cosvar/pyCV.py
src/cosvar/quickcv.py
src/cosvar/rz.py
cosvar-0.1.7.dist-info/LICENSE
cosvar-0.1.7.dist-info/METADATA
cosvar-0.1.7.dist-info/WHEEL
cosvar-0.1.7.dist-info/top_level.txt
cosvar-0.1.7.dist-info/RECORD
