Metadata-Version: 2.1
Name: cosvar
Version: 0.1.7
Summary: Python Cosmic Variance Calculator
Home-page: https://github.com/astrockragh/pyCV
Author: Christian Kragh Jespersen
Author-email: ckragh@princeton.edu
License: MIT
Classifier: Development Status :: 4 - Beta
Classifier: Intended Audience :: Science/Research
Classifier: Programming Language :: Python :: 3.8
License-File: LICENSE
Requires-Dist: pandas
Requires-Dist: numpy
Requires-Dist: scipy
